translation_manager/__init__.py
translation_manager/admin.py
translation_manager/apps.py
translation_manager/choices.py
translation_manager/defaults.py
translation_manager/filters.py
translation_manager/manager.py
translation_manager/models.py
translation_manager/serializers.py
translation_manager/settings.py
translation_manager/signals.py
translation_manager/tasks.py
translation_manager/tests.py
translation_manager/urls.py
translation_manager/utils.py
translation_manager/views.py
translation_manager/widgets.py
translation_manager/__pycache__/__init__.cpython-310.pyc
translation_manager/__pycache__/__init__.cpython-38.pyc
translation_manager/__pycache__/admin.cpython-310.pyc
translation_manager/__pycache__/admin.cpython-38.pyc
translation_manager/__pycache__/apps.cpython-310.pyc
translation_manager/__pycache__/apps.cpython-38.pyc
translation_manager/__pycache__/choices.cpython-310.pyc
translation_manager/__pycache__/choices.cpython-38.pyc
translation_manager/__pycache__/defaults.cpython-310.pyc
translation_manager/__pycache__/defaults.cpython-38.pyc
translation_manager/__pycache__/filters.cpython-310.pyc
translation_manager/__pycache__/filters.cpython-38.pyc
translation_manager/__pycache__/manager.cpython-310.pyc
translation_manager/__pycache__/manager.cpython-38.pyc
translation_manager/__pycache__/models.cpython-310.pyc
translation_manager/__pycache__/models.cpython-38.pyc
translation_manager/__pycache__/serializers.cpython-310.pyc
translation_manager/__pycache__/serializers.cpython-38.pyc
translation_manager/__pycache__/settings.cpython-310.pyc
translation_manager/__pycache__/settings.cpython-38.pyc
translation_manager/__pycache__/signals.cpython-310.pyc
translation_manager/__pycache__/signals.cpython-38.pyc
translation_manager/__pycache__/tasks.cpython-310.pyc
translation_manager/__pycache__/tasks.cpython-38.pyc
translation_manager/__pycache__/tests.cpython-38.pyc
translation_manager/__pycache__/urls.cpython-310.pyc
django_translation_manager-1.3.0.dist-info/METADATA
django_translation_manager-1.3.0.dist-info/WHEEL
django_translation_manager-1.3.0.dist-info/top_level.txt
django_translation_manager-1.3.0.dist-info/RECORD
