Metadata-Version: 2.1
Name: django-translation-manager
Version: 1.3.0
Summary: Django app for managing translations from admin
Home-page: https://github.com/COEXCZ/django-translation-manager
Author: Pavel Císař, Martin Kubát, Mikuláš Mrva, Jakub Ladra, Michal Kašpar, Jan Češpivo, Milan Vlasák - COEX s.r.o (http://www.coex.cz)
Author-email: pavel.cisar@coex.cz
License: Mozilla Public License 2.0 (MPL 2.0)
Platform: UNKNOWN
Classifier: Development Status :: 5 - Production/Stable
Classifier: Environment :: Web Environment
Classifier: Framework :: Django
Classifier: Intended Audience :: Developers
Classifier: License :: OSI Approved :: Mozilla Public License 2.0 (MPL 2.0)
Classifier: Operating System :: OS Independent
Classifier: Programming Language :: Python
Classifier: Topic :: Software Development :: Internationalization
